python_switchos/__init__.py
python_switchos/client.py
python_switchos/endpoint.py
python_switchos/http.py
python_switchos/utils.py
python_switchos/endpoints/__init__.py
python_switchos/endpoints/link.py
python_switchos/endpoints/poe.py
python_switchos/endpoints/sys.py
python_switchos-0.0.7.dist-info/METADATA
python_switchos-0.0.7.dist-info/WHEEL
python_switchos-0.0.7.dist-info/licenses/LICENSE
python_switchos-0.0.7.dist-info/RECORD
